<ScrollView>
    <GridLayout rows="auto, *" columns="*" class="stackStyle" >
        <SegmentedBar row="0" selectedIndex="{{ selectedIndexSpi }}">
            <SegmentedBar.items>
                <SegmentedBarItem title="Info" />
                <SegmentedBarItem title="Photos" />
            </SegmentedBar.items>
        </SegmentedBar>
        <StackLayout row="1" visibility="{{ isSpiInfoVisible ? 'visible' : 'collapsed' }}" >
            <Label text="{{ spiritDescription }}" class="p-16" textWrap="true"  />
        </StackLayout>
        <StackLayout row="1" visibility="{{ !isSpiInfoVisible ? 'visible' : 'collapsed' }}" >
            <DatePicker id="dt-spi" class="dt m-t-8 m-l-16 m-r-16"></DatePicker>
            <Button text="Explore Spirit Photos" class="btn btn-primary btn-active btn-picker" tap="{{ goToSpiritPage }}" />
        </StackLayout>
    </GridLayout>  
</ScrollView>